Workbook
Name Slicer_Catogery: #N/A
Name Slicer_City: #N/A
Name Slicer_Payment_Method: #N/A
Name Slicer_Salesperson: #N/A

Sheet Detail1
A1: Details for Sum of Revenue - Catogery: Accessories
A3: Order ID | B3: Prefix | C3: Year | D3: Order Number | E3: Date | F3: Customer name | G3: City | H3: Region | I3: Customer label | J3: Product Code | K3: Product name | L3: Catogery | M3: Units | N3: Unit price | O3: Cost per unit | P3: Salesperson | Q3: Payment Method | R3: Revenue | S3: Total cost | T3: Profit | U3: Profit margin | V3: Perfomance classification | W3: Transaction Review
A4: HYD25-001 | B4: HYD | C4: 25 | D4: 001 | E4: 45662 | F4: Rahul Sharma | G4: Hyderabad | H4: South | I4: Rahul Sharma - Hyderabad | J4: P101 | K4: Laptop Stand | L4: Accessories | M4: 2 | N4: 1200 | O4: 800 | P4: Rahul | Q4: UPI | R4: 2400 | S4: 1600 | T4: 800 | U4: 0.33333333 | V4: High Performance | W4: Normal
A5: MUM25-002 | B5: MUM | C5: 25 | D5: 002 | E5: 45663 | F5: Priya Reddy | G5: Mumbai | H5: West | I5: Priya Reddy - Mumbai | J5: P102 | K5: Wireless Mouse | L5: Accessories | M5: 3 | N5: 800 | O5: 450 | P5: Priya | Q5: Card | R5: 2400 | S5: 1350 | T5: 1050 | U5: 0.4375 | V5: High Performance | W5: Normal
A6: DEL25-003 | B6: DEL | C6: 25 | D6: 003 | E6: 45664 | F6: Aman Khan | G6: Delhi | H6: North | I6: Aman Khan - Delhi | J6: P103 | K6: Keyboard | L6: Accessories | M6: 1 | N6: 1500 | O6: 900 | P6: Aman | Q6: Cash | R6: 1500 | S6: 900 | T6: 600 | U6: 0.4 | V6: High Performance | W6: Normal
A7: MUM25-020 | B7: MUM | C7: 25 | D7: 020 | E7: 45681 | F7: Priya Reddy | G7: Mumbai | H7: West | I7: Priya Reddy - Mumbai | J7: P102 | K7: Wireless Mouse | L7: Accessories | M7: 1 | N7: 800 | O7: 450 | P7: Priya | Q7: Card | R7: 800 | S7: 450 | T7: 350 | U7: 0.4375 | V7: Regular | W7: Normal
A8: MUM25-005 | B8: MUM | C8: 25 | D8: 005 | E8: 45666 | F8: Arjun Mehta | G8: Mumbai | H8: West | I8: Arjun Mehta - Mumbai | J8: P101 | K8: Laptop Stand | L8: Accessories | M8: 1 | N8: 1200 | O8: 800 | P8: Priya | Q8: Card | R8: 1200 | S8: 800 | T8: 400 | U8: 0.33333333 | V8: High Performance | W8: Normal
A9: HYD25-019 | B9: HYD | C9: 25 | D9: 019 | E9: 45680 | F9: Rahul Sharma | G9: Hyderabad | H9: South | I9: Rahul Sharma - Hyderabad | J9: P101 | K9: Laptop Stand | L9: Accessories | M9: 2 | N9: 1200 | O9: 800 | P9: Rahul | Q9: UPI | R9: 2400 | S9: 1600 | T9: 800 | U9: 0.33333333 | V9: High Performance | W9: Normal
A10: HYD25-007 | B10: HYD | C10: 25 | D10: 007 | E10: 45668 | F10: Rohit Kumar | G10: Hyderabad | H10: South | I10: Rohit Kumar - Hyderabad | J10: P102 | K10: Wireless Mouse | L10: Accessories | M10: 2 | N10: 800 | O10: 450 | P10: Aman | Q10: Cash | R10: 1600 | S10: 900 | T10: 700 | U10: 0.4375 | V10: High Performance | W10: Normal
A11: DEL25-015 | B11: DEL | C11: 25 | D11: 015 | E11: 45676 | F11: Ravi Kumar | G11: Delhi | H11: North | I11: Ravi Kumar - Delhi | J11: P102 | K11: Wireless Mouse | L11: Accessories | M11: 4 | N11: 800 | O11: 450 | P11: Neha | Q11: Card | R11: 3200 | S11: 1800 | T11: 1400 | U11: 0.4375 | V11: High Performance | W11: Normal
A12: MUM25-014 | B12: MUM | C12: 25 | D12: 014 | E12: 45675 | F12: Nisha Das | G12: Mumbai | H12: West | I12: Nisha Das - Mumbai | J12: P103 | K12: Keyboard | L12: Accessories | M12: 2 | N12: 1500 | O12: 900 | P12: Priya | Q12: Cash | R12: 3000 | S12: 1800 | T12: 1200 | U12: 0.4 | V12: High Performance | W12: Normal
A13: HYD25-010 | B13: HYD | C13: 25 | D13: 010 | E13: 45671 | F13: Sana Khan | G13: Hyderabad | H13: South | I13: Sana Khan - Hyderabad | J13: P103 | K13: Keyboard | L13: Accessories | M13: 3 | N13: 1500 | O13: 900 | P13: Rahul | Q13: Cash | R13: 4500 | S13: 2700 | T13: 1800 | U13: 0.4 | V13: High Performance | W13: Normal
A14: HYD25-013 | B14: HYD | C14: 25 | D14: 013 | E14: 45674 | F14: Farhan Ali | G14: Hyderabad | H14: South | I14: Farhan Ali - Hyderabad | J14: P101 | K14: Laptop Stand | L14: Accessories | M14: 3 | N14: 1200 | O14: 800 | P14: Rahul | Q14: UPI | R14: 3600 | S14: 2400 | T14: 1200 | U14: 0.33333333 | V14: High Performance | W14: Normal

Sheet Pivot Analysis
A3: Row Labels | B3: Sum of Revenue | D3: Row Labels | E3: Sum of Profit | G3: Row Labels | H3: Sum of Units
A4: Delhi | B4: 49700 | D4: Delhi | E4: 17400 | G4: Card | H4: 15
A5: Hyderabad | B5: 67000 | D5: Hyderabad | E5: 21000 | G5: Cash | H5: 8
A6: Mumbai | B6: 62900 | D6: Mumbai | E6: 21000 | G6: UPI | H6: 23
A7: Grand Total | B7: 179600 | D7: Grand Total | E7: 59400 | G7: Grand Total | H7: 46
G9: Row Labels | H9: Sum of Revenue
G10: Accessories | H10: 10600
G11: Grand Total | H11: 10600
A12: Row Labels | B12: Sum of Revenue
A13: Headset | B13: 27000
A14: Keyboard | B14: 9000 | D14: Row Labels | E14: Sum of Revenue
A15: Laptop Stand | B15: 9600 | D15: Aman | E15: 13600 | G15: Row Labels | H15: Sum of Revenue
A16: Monitor | B16: 108000 | D16: Neha | E16: 48200 | G16: Card | H16: 57100
A17: Webcam | B17: 18000 | D17: Priya | E17: 56900 | G17: Cash | H17: 10600
A18: Wireless Mouse | B18: 8000 | D18: Rahul | E18: 60900 | G18: UPI | H18: 111900
A19: Grand Total | B19: 179600 | D19: Grand Total | E19: 179600 | G19: Grand Total | H19: 179600

Sheet Dashboard

Sheet Insights
A2: 1. Top Performing City
A4: Insight: Hyderabad generated the highest sales compared to Delhi and Mumbai.
A6: Evidence: The "Revenue by City" Pivot chart shows Hyderabad at the top with a total revenue of [67000].
A8: Business Meaning: Since there is strong demand in Hyderabad, launching new products or increasing marketing efforts in this region will likely boost profits further.
A10: 2. Best Selling Product
A12: Insight: Products like Monitors and Laptop Stands are the top performers in terms of sales.
A14: Evidence: The "Revenue by Product" chart indicates these items generated the highest revenue among all products.
A16: Business Meaning: High demand for these items means we must ensure they are never out of stock to avoid losing potential sales.
A18: 3. Payment Method Trend
A20: Insight: Customers highly prefer digital payments (UPI and Card) over Cash.
A22: Evidence: The "Revenue by Payment Method" chart highlights that the majority of revenue came through UPI and Cards.
A24: Business Meaning: Offering small discounts or cashbacks on digital payments can further improve customer satisfaction and increase sales volume.
... A47: marketing in top cities, maintain strict inventory control for best-sellers, and introduce combo offers for slow-moving products to accelerate overall company growth.

Sheet Clean data
A1: Order ID | B1: Prefix | C1: Year | D1: Order Number | E1: Date | F1: Customer name | G1: City | H1: Region | I1: Customer label | J1: Product Code | K1: Product name | L1: Catogery | M1: Units | N1: Unit price | O1: Cost per unit | P1: Salesperson | Q1: Payment Method | R1: Revenue | S1: Total cost | T1: Profit | U1: Profit margin | V1: Perfomance classification | W1: Transaction Review
A2: HYD25-001 | B2: =LEFT(A2, 3) -> HYD | C2: =MID(A2, 4, 2) -> 25 | D2: =RIGHT(A2, 3) -> 001 | E2: 45662 | F2: Rahul Sharma | G2: Hyderabad | H2: =_xlfn.XLOOKUP(G2, 'City Lookup'!A:A, 'City Lookup'!B:B) -> South | I2: =_xlfn.CONCAT(F2, " - ", G2) -> Rahul Sharma - Hyderabad | J2: P101 | K2: =_xlfn.XLOOKUP(J2, 'Product Lookup'!A:A, 'Product Lookup'!B:B) -> Laptop Stand | L2: =_xlfn.XLOOKUP(J2, 'Product Lookup'!A:A, 'Product Lookup'!C:C) -> Accessories | M2: 2 | N2: =_xlfn.XLOOKUP(J2, 'Product Lookup'!A:A, 'Product Lookup'!D:D) -> 1200 | O2: =_xlfn.XLOOKUP(J2, 'Product Lookup'!A:A, 'Product Lookup'!E:E) -> 800 | P2: Rahul | Q2: UPI | R2: =M2*N2 -> 2400 | S2: =M2*O2 -> 1600 | T2: =R2-S2 -> 800 | U2: =T2/R2 -> 0.33333333 | V2: =IF(R2>=1000, "High Performance", "Regular") -> High Performance | W2: =IF(OR(T2<0, R2<100), "Review", "Normal") -> Normal
A3: MUM25-002 | B3: =LEFT(A3, 3) -> MUM | C3: =MID(A3, 4, 2) -> 25 | D3: =RIGHT(A3, 3) -> 002 | E3: 45663 | F3: Priya Reddy | G3: Mumbai | H3: =_xlfn.XLOOKUP(G3, 'City Lookup'!A:A, 'City Lookup'!B:B) -> West | I3: =_xlfn.CONCAT(F3, " - ", G3) -> Priya Reddy - Mumbai | J3: P102 | K3: =_xlfn.XLOOKUP(J3, 'Product Lookup'!A:A, 'Product Lookup'!B:B) -> Wireless Mouse | L3: =_xlfn.XLOOKUP(J3, 'Product Lookup'!A:A, 'Product Lookup'!C:C) -> Accessories | M3: 3 | N3: =_xlfn.XLOOKUP(J3, 'Product Lookup'!A:A, 'Product Lookup'!D:D) -> 800 | O3: =_xlfn.XLOOKUP(J3, 'Product Lookup'!A:A, 'Product Lookup'!E:E) -> 450 | P3: Priya | Q3: Card | R3: =M3*N3 -> 2400 | S3: =M3*O3 -> 1350 | T3: =R3-S3 -> 1050 | U3: =T3/R3 -> 0.4375 | V3: =IF(R3>=1000, "High Performance", "Regular") -> High Performance | W3: =IF(OR(T3<0, R3<100), "Review", "Normal") -> Normal
A4: DEL25-003 | B4: =LEFT(A4, 3) -> DEL | C4: =MID(A4, 4, 2) -> 25 | D4: =RIGHT(A4, 3) -> 003 | E4: 45664 | F4: Aman Khan | G4: Delhi | H4: =_xlfn.XLOOKUP(G4, 'City Lookup'!A:A, 'City Lookup'!B:B) -> North | I4: =_xlfn.CONCAT(F4, " - ", G4) -> Aman Khan - Delhi | J4: P103 | K4: =_xlfn.XLOOKUP(J4, 'Product Lookup'!A:A, 'Product Lookup'!B:B) -> Keyboard | L4: =_xlfn.XLOOKUP(J4, 'Product Lookup'!A:A, 'Product Lookup'!C:C) -> Accessories | M4: 1 | N4: =_xlfn.XLOOKUP(J4, 'Product Lookup'!A:A, 'Product Lookup'!D:D) -> 1500 | O4: =_xlfn.XLOOKUP(J4, 'Product Lookup'!A:A, 'Product Lookup'!E:E) -> 900 | P4: Aman | Q4: Cash | R4: =M4*N4 -> 1500 | S4: =M4*O4 -> 900 | T4: =R4-S4 -> 600 | U4: =T4/R4 -> 0.4 | V4: =IF(R4>=1000, "High Performance", "Regular") -> High Performance | W4: =IF(OR(T4<0, R4<100), "Review", "Normal") -> Normal
A5: HYD25-004 | B5: =LEFT(A5, 3) -> HYD | C5: =MID(A5, 4, 2) -> 25 | D5: =RIGHT(A5, 3) -> 004 | E5: 45665 | F5: Sneha Rao | G5: Hyderabad | H5: =_xlfn.XLOOKUP(G5, 'City Lookup'!A:A, 'City Lookup'!B:B) -> South | I5: =_xlfn.CONCAT(F5, " - ", G5) -> Sneha Rao - Hyderabad | J5: P104 | K5: =_xlfn.XLOOKUP(J5, 'Product Lookup'!A:A, 'Product Lookup'!B:B) -> Monitor | L5: =_xlfn.XLOOKUP(J5, 'Product Lookup'!A:A, 'Product Lookup'!C:C) -> Electronics | M5: 4 | N5: =_xlfn.XLOOKUP(J5, 'Product Lookup'!A:A, 'Product Lookup'!D:D) -> 12000 | O5: =_xlfn.XLOOKUP(J5, 'Product Lookup'!A:A, 'Product Lookup'!E:E) -> 8500 | P5: Rahul | Q5: UPI | R5: =M5*N5 -> 48000 | S5: =M5*O5 -> 34000 | T5: =R5-S5 -> 14000 | U5: =T5/R5 -> 0.29166667 | V5: =IF(R5>=1000, "High Performance", "Regular") -> High Performance | W5: =IF(OR(T5<0, R5<100), "Review", "Normal") -> Normal
A6: MUM25-005 | B6: =LEFT(A6, 3) -> MUM | C6: =MID(A6, 4, 2) -> 25 | D6: =RIGHT(A6, 3) -> 005 | E6: 45666 | F6: Arjun Mehta | G6: Mumbai | H6: =_xlfn.XLOOKUP(G6, 'City Lookup'!A:A, 'City Lookup'!B:B) -> West | I6: =_xlfn.CONCAT(F6, " - ", G6) -> Arjun Mehta - Mumbai | J6: P101 | K6: =_xlfn.XLOOKUP(J6, 'Product Lookup'!A:A, 'Product Lookup'!B:B) -> Laptop Stand | L6: =_xlfn.XLOOKUP(J6, 'Product Lookup'!A:A, 'Product Lookup'!C:C) -> Accessories | M6: 1 | N6: =_xlfn.XLOOKUP(J6, 'Product Lookup'!A:A, 'Product Lookup'!D:D) -> 1200 | O6: =_xlfn.XLOOKUP(J6, 'Product Lookup'!A:A, 'Product Lookup'!E:E) -> 800 | P6: Priya | Q6: Card | R6: =M6*N6 -> 1200 | S6: =M6*O6 -> 800 | T6: =R6-S6 -> 400 | U6: =T6/R6 -> 0.33333333 | V6: =IF(R6>=1000, "High Performance", "Regular") -> High Performance | W6: =IF(OR(T6<0, R6<100), "Review", "Normal") -> Normal
A7: DEL25-006 | B7: =LEFT(A7, 3) -> DEL | C7: =MID(A7, 4, 2) -> 25 | D7: =RIGHT(A7, 3) -> 006 | E7: 45667 | F7: Ayesha Ali | G7: Delhi | H7: =_xlfn.XLOOKUP(G7, 'City Lookup'!A:A, 'City Lookup'!B:B) -> North | I7: =_xlfn.CONCAT(F7, " - ", G7) -> Ayesha Ali - Delhi | J7: P105 | K7: =_xlfn.XLOOKUP(J7, 'Product Lookup'!A:A, 'Product Lookup'!B:B) -> Headset | L7: =_xlfn.XLOOKUP(J7, 'Product Lookup'!A:A, 'Product Lookup'!C:C) -> Electronics | M7: 5 | N7: =_xlfn.XLOOKUP(J7, 'Product Lookup'!A:A, 'Product Lookup'!D:D) -> 3000 | O7: =_xlfn.XLOOKUP(J7, 'Product Lookup'!A:A, 'Product Lookup'!E:E) -> 1800 | P7: Neha | Q7: UPI | R7: =M7*N7 -> 15000 | S7: =M7*O7 -> 9000 | T7: =R7-S7 -> 6000 | U7: =T7/R7 -> 0.4 | V7: =IF(R7>=1000, "High Performance", "Regular") -> High Performance | W7: =IF(OR(T7<0, R7<100), "Review", "Normal") -> Normal
A8: HYD25-007 | B8: =LEFT(A8, 3) -> HYD | C8: =MID(A8, 4, 2) -> 25 | D8: =RIGHT(A8, 3) -> 007 | E8: 45668 | F8: Rohit Kumar | G8: Hyderabad | H8: =_xlfn.XLOOKUP(G8, 'City Lookup'!A:A, 'City Lookup'!B:B) -> South | I8: =_xlfn.CONCAT(F8, " - ", G8) -> Rohit Kumar - Hyderabad | J8: P102 | K8: =_xlfn.XLOOKUP(J8, 'Product Lookup'!A:A, 'Product Lookup'!B:B) -> Wireless Mouse | L8: =_xlfn.XLOOKUP(J8, 'Product Lookup'!A:A, 'Product Lookup'!C:C) -> Accessories | M8: 2 | N8: =_xlfn.XLOOKUP(J8, 'Product Lookup'!A:A, 'Product Lookup'!D:D) -> 800 | O8: =_xlfn.XLOOKUP(J8, 'Product Lookup'!A:A, 'Product Lookup'!E:E) -> 450 | P8: Aman | Q8: Cash | R8: =M8*N8 -> 1600 | S8: =M8*O8 -> 900 | T8: =R8-S8 -> 700 | U8: =T8/R8 -> 0.4375 | V8: =IF(R8>=1000, "High Performance", "Regular") -> High Performance | W8: =IF(OR(T8<0, R8<100), "Review", "Normal") -> Normal
A9: MUM25-008 | B9: =LEFT(A9, 3) -> MUM | C9: =MID(A9, 4, 2) -> 25 | D9: =RIGHT(A9, 3) -> 008 | E9: 45669 | F9: Neha Verma | G9: Mumbai | H9: =_xlfn.XLOOKUP(G9, 'City Lookup'!A:A, 'City Lookup'!B:B) -> West | I9: =_xlfn.CONCAT(F9, " - ", G9) -> Neha Verma - Mumbai | J9: P106 | K9: =_xlfn.XLOOKUP(J9, 'Product Lookup'!A:A, 'Product Lookup'!B:B) -> Webcam | L9: =_xlfn.XLOOKUP(J9, 'Product Lookup'!A:A, 'Product Lookup'!C:C) -> Electronics | M9: 3 | N9: =_xlfn.XLOOKUP(J9, 'Product Lookup'!A:A, 'Product Lookup'!D:D) -> 4500 | O9: =_xlfn.XLOOKUP(J9, 'Product Lookup'!A:A, 'Product Lookup'!E:E) -> 2800 | P9: Priya | Q9: Card | R9: =M9*N9 -> 13500 | S9: =M9*O9 -> 8400 | T9: =R9-S9 -> 5100 | U9: =T9/R9 -> 0.37777778 | V9: =IF(R9>=1000, "High Performance", "Regular") -> High Performance | W9: =IF(OR(T9<0, R9<100), "Review", "Normal") -> Normal
A10: DEL25-009 | B10: =LEFT(A10, 3) -> DEL | C10: =MID(A10, 4, 2) -> 25 | D10: =RIGHT(A10, 3) -> 009 | E10: 45670 | F10: Kiran Rao | G10: Delhi | H10: =_xlfn.XLOOKUP(G10, 'City Lookup'!A:A, 'City Lookup'!B:B) -> North | I10: =_xlfn.CONCAT(F10, " - ", G10) -> Kiran Rao - Delhi | J10: P104 | K10: =_xlfn.XLOOKUP(J10, 'Product Lookup'!A:A, 'Product Lookup'!B:B) -> Monitor | L10: =_xlfn.XLOOKUP(J10, 'Product Lookup'!A:A, 'Product Lookup'!C:C) -> Electronics | M10: 2 | N10: =_xlfn.XLOOKUP(J10, 'Product Lookup'!A:A, 'Product Lookup'!D:D) -> 12000 | O10: =_xlfn.XLOOKUP(J10, 'Product Lookup'!A:A, 'Product Lookup'!E:E) -> 8500 | P10: Neha | Q10: UPI | R10: =M10*N10 -> 24000 | S10: =M10*O10 -> 17000 | T10: =R10-S10 -> 7000 | U10: =T10/R10 -> 0.29166667 | V10: =IF(R10>=1000, "High Performance", "Regular") -> High Performance | W10: =IF(OR(T10<0, R10<100), "Review", "Normal") -> Normal
A11: HYD25-010 | B11: =LEFT(A11, 3) -> HYD | C11: =MID(A11, 4, 2) -> 25 | D11: =RIGHT(A11, 3) -> 010 | E11: 45671 | F11: Sana Khan | G11: Hyderabad | H11: =_xlfn.XLOOKUP(G11, 'City Lookup'!A:A, 'City Lookup'!B:B) -> South | I11: =_xlfn.CONCAT(F11, " - ", G11) -> Sana Khan - Hyderabad | J11: P103 | K11: =_xlfn.XLOOKUP(J11, 'Product Lookup'!A:A, 'Product Lookup'!B:B) -> Keyboard | L11: =_xlfn.XLOOKUP(J11, 'Product Lookup'!A:A, 'Product Lookup'!C:C) -> Accessories | M11: 3 | N11: =_xlfn.XLOOKUP(J11, 'Product Lookup'!A:A, 'Product Lookup'!D:D) -> 1500 | O11: =_xlfn.XLOOKUP(J11, 'Product Lookup'!A:A, 'Product Lookup'!E:E) -> 900 | P11: Rahul | Q11: Cash | R11: =M11*N11 -> 4500 | S11: =M11*O11 -> 2700 | T11: =R11-S11 -> 1800 | U11: =T11/R11 -> 0.4 | V11: =IF(R11>=1000, "High Performance", "Regular") -> High Performance | W11: =IF(OR(T11<0, R11<100), "Review", "Normal") -> Normal
A12: MUM25-011 | B12: =LEFT(A12, 3) -> MUM | C12: =MID(A12, 4, 2) -> 25 | D12: =RIGHT(A12, 3) -> 011 | E12: 45672 | F12: Vivek Patel | G12: Mumbai | H12: =_xlfn.XLOOKUP(G12, 'City Lookup'!A:A, 'City Lookup'!B:B) -> West | I12: =_xlfn.CONCAT(F12, " - ", G12) -> Vivek Patel - Mumbai | J12: P105 | K12: =_xlfn.XLOOKUP(J12, 'Product Lookup'!A:A, 'Product Lookup'!B:B) -> Headset | L12: =_xlfn.XLOOKUP(J12, 'Product Lookup'!A:A, 'Product Lookup'!C:C) -> Electronics | M12: 2 | N12: =_xlfn.XLOOKUP(J12, 'Product Lookup'!A:A, 'Product Lookup'!D:D) -> 3000 | O12: =_xlfn.XLOOKUP(J12, 'Product Lookup'!A:A, 'Product Lookup'!E:E) -> 1800 | P12: Aman | Q12: UPI | R12: =M12*N12 -> 6000 | S12: =M12*O12 -> 3600 | T12: =R12-S12 -> 2400 | U12: =T12/R12 -> 0.4 | V12: =IF(R12>=1000, "High Performance", "Regular") -> High Performance | W12: =IF(OR(T12<0, R12<100), "Review", "Normal") -> Normal
A13: HYD25-013 | B13: =LEFT(A13, 3) -> HYD | C13: =MID(A13, 4, 2) -> 25 | D13: =RIGHT(A13, 3) -> 013 | E13: 45674 | F13: Farhan Ali | G13: Hyderabad | H13: =_xlfn.XLOOKUP(G13, 'City Lookup'!A:A, 'City Lookup'!B:B) -> South | I13: =_xlfn.CONCAT(F13, " - ", G13) -> Farhan Ali - Hyderabad | J13: P101 | K13: =_xlfn.XLOOKUP(J13, 'Product Lookup'!A:A, 'Product Lookup'!B:B) -> Laptop Stand | L13: =_xlfn.XLOOKUP(J13, 'Product Lookup'!A:A, 'Product Lookup'!C:C) -> Accessories | M13: 3 | N13: =_xlfn.XLOOKUP(J13, 'Product Lookup'!A:A, 'Product Lookup'!D:D) -> 1200 | O13: =_xlfn.XLOOKUP(J13, 'Product Lookup'!A:A, 'Product Lookup'!E:E) -> 800 | P13: Rahul | Q13: UPI | R13: =M13*N13 -> 3600 | S13: =M13*O13 -> 2400 | T13: =R13-S13 -> 1200 | U13: =T13/R13 -> 0.33333333 | V13: =IF(R13>=1000, "High Performance", "Regular") -> High Performance | W13: =IF(OR(T13<0, R13<100), "Review", "Normal") -> Normal
... A20: MUM25-020 | B20: =LEFT(A20, 3) -> MUM | C20: =MID(A20, 4, 2) -> 25 | D20: =RIGHT(A20, 3) -> 020 | E20: 45681 | F20: Priya Reddy | G20: Mumbai | H20: =_xlfn.XLOOKUP(G20, 'City Lookup'!A:A, 'City Lookup'!B:B) -> West | I20: =_xlfn.CONCAT(F20, " - ", G20) -> Priya Reddy - Mumbai | J20: P102 | K20: =_xlfn.XLOOKUP(J20, 'Product Lookup'!A:A, 'Product Lookup'!B:B) -> Wireless Mouse | L20: =_xlfn.XLOOKUP(J20, 'Product Lookup'!A:A, 'Product Lookup'!C:C) -> Accessories | M20: 1 | N20: =_xlfn.XLOOKUP(J20, 'Product Lookup'!A:A, 'Product Lookup'!D:D) -> 800 | O20: =_xlfn.XLOOKUP(J20, 'Product Lookup'!A:A, 'Product Lookup'!E:E) -> 450 | P20: Priya | Q20: Card | R20: =M20*N20 -> 800 | S20: =M20*O20 -> 450 | T20: =R20-S20 -> 350 | U20: =T20/R20 -> 0.4375 | V20: =IF(R20>=1000, "High Performance", "Regular") -> Regular | W20: =IF(OR(T20<0, R20<100), "Review", "Normal") -> Normal

Sheet Calculations
A1: Total Revenue | B1: Total Profit | C1: Total Units Sold | D1: Number of Transactions | E1: Average Revenue per Transaction | F1: Average Profit per Transaction
A2: =SUM('Clean data'!R:R) -> 179600 | B2: =SUM('Clean data'!T:T) -> 59400 | C2: =SUM('Clean data'!M:M) -> 46 | D2: =COUNTA('Clean data'!A:A) - 1 -> 19 | E2: =AVERAGE('Clean data'!R:R) -> 9452.6316 | F2: =AVERAGE('Clean data'!S:S) -> 6326.3158

Sheet Raw Data
A1: Order ID | B1: Date | C1: Customer Name | D1: City | E1: Product Code | F1: Units | G1: Salesperson | H1: Payment Method
A2: HYD25-001 | B2: 45662 | C2: rahul sharma | D2: Hyderabad | E2: P101 | F2: 2 | G2: Rahul | H2: UPI
A3: MUM25-002 | B3: 45663 | C3: Priya reddy | D3: Mumbai | E3: P102 | F3: 3 | G3: Priya | H3: Card
A4: DEL25-003 | B4: 45664 | C4: AMAn khan | D4: Delhi | E4: P103 | F4: 1 | G4: Aman | H4: Cash
A5: HYD25-004 | B5: 45665 | C5: Sneha Rao | D5: Hyderabad | E5: P104 | F5: 4 | G5: Rahul | H5: UPI
A6: MUM25-005 | B6: 45666 | C6: Arjun Mehta | D6: Mumbai | E6: P101 | F6: 1 | G6: Priya | H6: Card
A7: DEL25-006 | B7: 45667 | C7: Ayesha ali | D7: Delhi | E7: P105 | F7: 5 | G7: Neha | H7: UPI
A8: HYD25-007 | B8: 45668 | C8: Rohit kumar | D8: Hyderabad | E8: P102 | F8: 2 | G8: Aman | H8: Cash
A9: MUM25-008 | B9: 45669 | C9: Neha Verma | D9: Mumbai | E9: P106 | F9: 3 | G9: Priya | H9: Card
A10: DEL25-009 | B10: 45670 | C10: kiran Rao | D10: Delhi | E10: P104 | F10: 2 | G10: Neha | H10: UPI
A11: HYD25-010 | B11: 45671 | C11: Sana khan | D11: Hyderabad | E11: P103 | F11: 3 | G11: Rahul | H11: Cash
A12: MUM25-011 | B12: 45672 | C12: Vivek Patel | D12: Mumbai | E12: P105 | F12: 2 | G12: Aman | H12: UPI
A13: DEL25-012 | B13: 45673 | C13: Meera Singh | D13: Delhi | E13: P106 | F13: 4 | G13: Neha
A14: HYD25-013 | B14: 45674 | C14: Farhan Ali | D14: Hyderabad | E14: P101 | F14: 3 | G14: Rahul | H14: UPI
A15: MUM25-014 | B15: 45675 | C15: Nisha Das | D15: Mumbai | E15: P103 | F15: 2 | G15: Priya | H15: Cash
A16: DEL25-015 | B16: 45676 | C16: Ravi Kumar | D16: Delhi | E16: P102 | F16: 4 | G16: Neha | H16: Card
A17: HYD25-016 | B17: 45677 | C17: Pooja Rao | D17: Hyderabad | E17: P106 | F17: 1 | G17: Aman | H17: UPI
A18: MUM25-017 | B18: 45678 | C18: Imran Khan | D18: Mumbai | E18: P104 | F18: 3 | G18: Priya | H18: Card
A19: DEL25-018 | B19: 45679 | C19: Divya Shah | D19: Delhi | E19: P105 | F19: 2 | G19: Neha | H19: UPI
A20: HYD25-019 | B20: 45680 | C20: Rahul Sharma | D20: Hyderabad | E20: P101 | F20: 2 | G20: Rahul | H20: UPI
A21: HYD25-019 | B21: 45680 | C21: Rahul Sharma | D21: Hyderabad | E21: P101 | F21: 2 | G21: Rahul | H21: UPI
A22: MUM25-020 | B22: 45681 | C22: Priya Reddy | D22: Mumbai | E22: P102 | F22: 1 | G22: Priya | H22: Card

Sheet Product Lookup
A1: Product Code | B1: Product | C1: Category | D1: Unit Price | E1: Cost Per Unit
A2: P101 | B2: Laptop Stand | C2: Accessories | D2: 1200 | E2: 800
A3: P102 | B3: Wireless Mouse | C3: Accessories | D3: 800 | E3: 450
A4: P103 | B4: Keyboard | C4: Accessories | D4: 1500 | E4: 900
A5: P104 | B5: Monitor | C5: Electronics | D5: 12000 | E5: 8500
A6: P105 | B6: Headset | C6: Electronics | D6: 3000 | E6: 1800
A7: P106 | B7: Webcam | C7: Electronics | D7: 4500 | E7: 2800

Sheet City Lookup
A1: City | B1: Region
A2: Hyderabad | B2: South
A3: Mumbai | B3: West
A4: Delhi | B4: North
